navesitas/__init__.py
navesitas/naves.py
navesitas/utils.py
navesitas-0.1.0.dist-info/METADATA
navesitas-0.1.0.dist-info/WHEEL
navesitas-0.1.0.dist-info/top_level.txt
navesitas-0.1.0.dist-info/RECORD
