Metadata-Version: 2.4
Name: navesitas
Version: 0.1.0
Summary: Unos videitos cortitos de puras naves!
Home-page: https://www.youtube.com
Author: Bastian Adasme
Dynamic: author
Dynamic: description
Dynamic: description-content-type
Dynamic: home-page
Dynamic: summary
